{
	"credit": "Made with Blockbench",
	"render_type": "cutout",
	"textures": {
		"concrete": "block/black_concrete",
		"particle": "block/iron_block",
		"2_0": "block/iron_block"
	},
	"elements": [
		{
			"name": "fond",
			"from": [1, 0, 6],
			"to": [15, 6, 7],
			"faces": {
				"north": {"uv": [0, 0, 14, 6], "texture": "#concrete"},
				"east": {"uv": [0, 0, 1, 6], "texture": "#concrete"},
				"south": {"uv": [0, 0, 14, 6], "texture": "#concrete"},
				"west": {"uv": [0, 0, 1, 6], "texture": "#concrete"},
				"up": {"uv": [0, 0, 14, 1], "texture": "#concrete"},
				"down": {"uv": [0, 0, 14, 1], "texture": "#concrete"}
			}
		},
		{
			"from": [7, 0, 7],
			"to": [9, 6, 9],
			"faces": {
				"north": {"uv": [6, 0, 8, 16], "texture": "#2_0"},
				"east": {"uv": [4, 0, 6, 16], "texture": "#2_0"},
				"south": {"uv": [2, 0, 4, 16], "texture": "#2_0"},
				"west": {"uv": [8, 0, 10, 16], "texture": "#2_0"},
				"up": {"uv": [0, 0, 2, 2], "texture": "#2_0"},
				"down": {"uv": [0, 0, 2, 2], "texture": "#2_0"}
			}
		},
		{
			"name": "cubehor1",
			"from": [3.25, 2.5, 7],
			"to": [12.75, 3.5, 7.5],
			"faces": {
				"north": {"uv": [4, 0, 7.5, 1], "texture": "#2_0"},
				"east": {"uv": [4, 0, 4.5, 1], "texture": "#2_0"},
				"south": {"uv": [4, 0, 7.5, 1], "texture": "#2_0"},
				"west": {"uv": [4, 0, 4.5, 1], "texture": "#2_0"},
				"up": {"uv": [4, 0, 7.5, 0.5], "texture": "#2_0"},
				"down": {"uv": [4, 0, 7.5, 0.5], "texture": "#2_0"}
			}
		},
		{
			"name": "bottom",
			"from": [1, 0, 5],
			"to": [15, 1, 6],
			"faces": {
				"north": {"uv": [0, 0, 14, 1], "texture": "#concrete"},
				"east": {"uv": [0, 0, 1, 1], "texture": "#concrete"},
				"south": {"uv": [0, 0, 14, 1], "texture": "#concrete"},
				"west": {"uv": [0, 0, 1, 1], "texture": "#concrete"},
				"up": {"uv": [0, 0, 14, 1], "texture": "#concrete"},
				"down": {"uv": [0, 0, 14, 1], "texture": "#concrete"}
			}
		},
		{
			"name": "bottom",
			"from": [1, 5, 3],
			"to": [15, 6, 6],
			"faces": {
				"north": {"uv": [0, 0, 14, 1], "texture": "#concrete"},
				"east": {"uv": [0, 0, 3, 1], "texture": "#concrete"},
				"south": {"uv": [0, 0, 14, 1], "texture": "#concrete"},
				"west": {"uv": [0, 0, 3, 1], "texture": "#concrete"},
				"up": {"uv": [0, 0, 14, 3], "texture": "#concrete"},
				"down": {"uv": [0, 0, 14, 3], "texture": "#concrete"}
			}
		},
		{
			"name": "right",
			"from": [1, 1, 5],
			"to": [2, 5, 6],
			"faces": {
				"north": {"uv": [0, 0, 1, 4], "texture": "#concrete"},
				"east": {"uv": [0, 0, 1, 4], "texture": "#concrete"},
				"south": {"uv": [0, 0, 1, 4], "texture": "#concrete"},
				"west": {"uv": [0, 0, 1, 4], "texture": "#concrete"},
				"up": {"uv": [0, 0, 1, 1], "texture": "#concrete"},
				"down": {"uv": [0, 0, 1, 1], "texture": "#concrete"}
			}
		},
		{
			"name": "left",
			"from": [14, 1, 5],
			"to": [15, 5, 6],
			"faces": {
				"north": {"uv": [0, 0, 1, 4], "texture": "#concrete"},
				"east": {"uv": [0, 0, 1, 4], "texture": "#concrete"},
				"south": {"uv": [0, 0, 1, 4], "texture": "#concrete"},
				"west": {"uv": [0, 0, 1, 4], "texture": "#concrete"},
				"up": {"uv": [0, 0, 1, 1], "texture": "#concrete"},
				"down": {"uv": [0, 0, 1, 1], "texture": "#concrete"}
			}
		}
	],
	"groups": [
		0,
		1,
		2,
		{
			"name": "bottom",
			"origin": [8, 8, 8],
			"color": 0,
			"children": [3, 4]
		},
		{
			"name": "middle",
			"origin": [8, 8, 8],
			"color": 0,
			"children": [5]
		},
		{
			"name": "top",
			"origin": [8, 8, 8],
			"color": 0,
			"children": [6]
		}
	]
}